bitcoinutils/__init__.py
bitcoinutils/bech32.py
bitcoinutils/constants.py
bitcoinutils/keys.py
bitcoinutils/script.py
bitcoinutils/setup.py
bitcoinutils/transactions.py
bitcoinutils/utils.py
bitcoin_utils_fork_minimal-0.4.11.6.dist-info/LICENSE
bitcoin_utils_fork_minimal-0.4.11.6.dist-info/METADATA
bitcoin_utils_fork_minimal-0.4.11.6.dist-info/WHEEL
bitcoin_utils_fork_minimal-0.4.11.6.dist-info/top_level.txt
bitcoin_utils_fork_minimal-0.4.11.6.dist-info/RECORD
