Metadata-Version: 2.1
Name: bitcoin-utils-fork-minimal
Version: 0.4.11.6
Summary: Bitcoin utility functions
Home-page: https://github.com/doersf/python-bitcoin-utils
Author: Konstantinos Karasavvas
Author-email: kkarasavvas@gmail.com
License: AGPLv3
Keywords: bitcoin library utilities tools
License-File: LICENSE
